tqec/__init__.py
tqec/_cli/subcommands/base.py
tqec/_cli/subcommands/check_dae.py
tqec/_cli/subcommands/dae2circuits.py
tqec/_cli/subcommands/dae2observables.py
tqec/_cli/subcommands/run_example.py
tqec/_cli/subcommands/viz.py
tqec/_cli/tqec.py
tqec/_version.py
tqec/circuit/__init__.py
tqec/circuit/measurement.py
tqec/circuit/measurement_map.py
tqec/circuit/moment.py
tqec/circuit/qubit.py
tqec/circuit/qubit_map.py
tqec/circuit/schedule/__init__.py
tqec/circuit/schedule/circuit.py
tqec/circuit/schedule/exception.py
tqec/circuit/schedule/manipulation.py
tqec/circuit/schedule/schedule.py
tqec/compile/__init__.py
tqec/compile/blocks/__init__.py
tqec/compile/blocks/block.py
tqec/compile/blocks/enums.py
tqec/compile/blocks/layers/__init__.py
tqec/compile/blocks/layers/atomic/__init__.py
tqec/compile/blocks/layers/atomic/base.py
tqec/compile/blocks/layers/atomic/layout.py
tqec/compile/blocks/layers/atomic/plaquettes.py
tqec/compile/blocks/layers/atomic/raw.py
tqec/compile/blocks/layers/composed/__init__.py
tqec/compile/blocks/layers/composed/base.py
tqec/compile/blocks/layers/composed/repeated.py
tqec/compile/blocks/layers/composed/sequenced.py
tqec/compile/blocks/layers/merge.py
tqec/compile/blocks/layers/spatial.py
tqec/compile/blocks/layers/temporal.py
tqec/compile/blocks/positioning.py
tqec/compile/compile.py
tqec/compile/convention.py
tqec/compile/detectors/__init__.py
tqec/compile/detectors/compute.py
tqec/compile/detectors/database.py
tqec/compile/detectors/detector.py
tqec/compile/generation.py
tqec/compile/graph.py
tqec/compile/observables/__init__.py
tqec/compile/observables/abstract_observable.py
tqec/compile/observables/builder.py
tqec/compile/observables/fixed_boundary_builder.py
tqec/compile/observables/fixed_bulk_builder.py
tqec/compile/specs/__init__.py
tqec/compile/specs/base.py
tqec/compile/specs/enums.py
tqec/compile/specs/library/__init__.py
tqec/compile/specs/library/fixed_boundary.py
tqec/compile/specs/library/fixed_bulk.py
tqec-0.1.0.dist-info/licenses/LICENSE
tqec-0.1.0.dist-info/WHEEL
tqec-0.1.0.dist-info/entry_points.txt
tqec-0.1.0.dist-info/METADATA
tqec-0.1.0.dist-info/RECORD
