Metadata-Version: 2.4
Name: tqec
Version: 0.1.0
Summary: A design automation framework for Topological Quantum Error Correction.
Keywords: topological quantum error correction,qec
Author: TQEC community
Author-email: TQEC community <tqec-design-automation@googlegroups.com>
License-Expression: Apache-2.0
License-File: LICENSE
Classifier: Development Status :: 4 - Beta
Classifier: Intended Audience :: Developers
Classifier: Intended Audience :: Science/Research
Classifier: License :: OSI Approved :: Apache Software License
Classifier: Natural Language :: English
Classifier: Operating System :: Microsoft :: Windows
Classifier: Operating System :: MacOS
Classifier: Operating System :: POSIX :: Linux
Classifier: Programming Language :: JavaScript
Classifier: Programming Language :: Python :: 3 :: Only
Classifier: Programming Language :: Python :: 3.10
Classifier: Programming Language :: Python :: 3.11
Classifier: Programming Language :: Python :: 3.12
Classifier: Programming Language :: Python :: 3.13
Classifier: Topic :: Scientific/Engineering
Classifier: Topic :: Scientific/Engineering :: Quantum Computing
Classifier: Topic :: Software Development :: Libraries
Classifier: Topic :: Software Development :: User Interfaces
Classifier: Topic :: Utilities
Classifier: Typing :: Typed
Requires-Dist: matplotlib>=3.9
Requires-Dist: networkx>=3.0
Requires-Dist: numpy>=1.22,<2.3
Requires-Dist: numpy>=1.24 ; python_full_version >= '3.11'
Requires-Dist: numpy>=1.26 ; python_full_version >= '3.12'
Requires-Dist: numpy>=2.1 ; python_full_version >= '3.13'
Requires-Dist: platformdirs>=4.0
Requires-Dist: pycollada>=0.8
Requires-Dist: pycryptosat>=5.11.21
Requires-Dist: python-sat[cryptosat]>=1.8.dev20
Requires-Dist: pymatching>=2.3.1
Requires-Dist: pyzx>=0.9.0
Requires-Dist: scipy>=1.15
Requires-Dist: semver>=3.0.0
Requires-Dist: sinter>=1.14
Requires-Dist: sphinx-design>=0.6.1
Requires-Dist: stim>=1.14
Requires-Dist: stim>=1.15 ; python_full_version >= '3.13'
Requires-Dist: svg-py>=1.8.0
Requires-Dist: tqecd>=0.1.3
Requires-Dist: typing-extensions>=4.2
Requires-Dist: typing-extensions>=4.12 ; python_full_version >= '3.13'
Requires-Python: >=3.10, <3.14
Project-URL: Documentation, https://tqec.github.io/tqec/
Project-URL: Issues, https://github.com/tqec/tqec/issues
Project-URL: Repository, https://github.com/tqec/tqec
Project-URL: Website, https://tqec.app
